ai/backend/helpers/VERSION
ai/backend/helpers/__init__.py
ai/backend/helpers/package.py
backend_ai_kernel_helper-26.1.0.dist-info/METADATA
backend_ai_kernel_helper-26.1.0.dist-info/WHEEL
backend_ai_kernel_helper-26.1.0.dist-info/namespace_packages.txt
backend_ai_kernel_helper-26.1.0.dist-info/top_level.txt
backend_ai_kernel_helper-26.1.0.dist-info/RECORD
